getthenews/__init__.py
getthenews/main.py
getthenews/utils/__init__.py
getthenews/utils/command_line.py
getthenews/utils/soup.py
getthenews-0.1.1.dist-info/entry_points.txt
getthenews-0.1.1.dist-info/LICENSE
getthenews-0.1.1.dist-info/WHEEL
getthenews-0.1.1.dist-info/METADATA
getthenews-0.1.1.dist-info/RECORD
